louay_ml_library/__init__.py
louay_ml_library/utils.py
louay_ml_library/activations/__init__.py
louay_ml_library/activations/leaky_relu.py
louay_ml_library/activations/relu.py
louay_ml_library/activations/sigmoid.py
louay_ml_library/activations/sign.py
louay_ml_library/activations/softmax.py
louay_ml_library/activations/tanh.py
louay_ml_library/base/__init__.py
louay_ml_library/base/activation.py
louay_ml_library/base/loss.py
louay_ml_library/base/model.py
louay_ml_library/base/optimizer.py
louay_ml_library/losses/__init__.py
louay_ml_library/losses/bce.py
louay_ml_library/losses/cross_entropy.py
louay_ml_library/losses/mae.py
louay_ml_library/losses/mse.py
louay_ml_library/models/__init__.py
louay_ml_library/models/decision_tree.py
louay_ml_library/models/linear_regression.py
louay_ml_library/models/mlp.py
louay_ml_library/models/perceptron.py
louay_ml_library/models/svm.py
louay_ml_library/optimizers/__init__.py
louay_ml_library/optimizers/adam.py
louay_ml_library/optimizers/rms_prop.py
louay_ml_library/optimizers/sgd.py
louay_ml_library/tests/__init__.py
louay_ml_library/tests/test_decision_tree.py
louay_ml_library/tests/test_helpers.py
louay_ml_library/tests/test_linear_regression.py
louay_ml_library/tests/test_mlp.py
louay_ml_library/tests/test_perceptropn.py
louay_ml_library/tests/test_svm.py
louay_ml_library-0.0.3.dist-info/LICENCE.txt
louay_ml_library-0.0.3.dist-info/METADATA
louay_ml_library-0.0.3.dist-info/WHEEL
louay_ml_library-0.0.3.dist-info/top_level.txt
louay_ml_library-0.0.3.dist-info/RECORD
