Metadata-Version: 2.1
Name: louay_ml_library
Version: 0.0.3
Summary: A custom machine learning library containing several models
Home-page: https://github.com/louay01/louay_ml_library
Author: Louay El Masri
Author-email: masrilouay5@gmai.com
License: MIT
Keywords: machine learning linear regression linear classifier neural networks decision trees SVM AI
Classifier: Development Status :: 4 - Beta
Classifier: Intended Audience :: Education
Classifier: Intended Audience :: Science/Research
Classifier: Operating System :: OS Independent
Classifier: License :: OSI Approved :: MIT License
Classifier: Programming Language :: Python :: 3
License-File: LICENCE.txt
